calcbsimpvol/__init__.py
calcbsimpvol/data/__init__.py
calcbsimpvol/examples/__init__.py
calcbsimpvol/examples/example1.py
calcbsimpvol/examples/example2.py
calcbsimpvol/examples/example3.py
calcbsimpvol/src/__init__.py
calcbsimpvol/src/calcbsimpvol.py
calcbsimpvol-1.14.0.dist-info/LICENSE
calcbsimpvol-1.14.0.dist-info/METADATA
calcbsimpvol-1.14.0.dist-info/WHEEL
calcbsimpvol-1.14.0.dist-info/top_level.txt
calcbsimpvol-1.14.0.dist-info/RECORD
