Metadata-Version: 2.1
Name: calcbsimpvol
Version: 1.14.0
Summary: Calculate Black Scholes Implied Volatility - Vectorwise 
Home-page: https://erkandem.github.io/calcbsimpvol/
Author: Erkan Demiralay
Author-email: erkan.dem@pm.me
License: MIT
Project-URL: Documentation, https://erkandem.github.io/calcbsimpvol/
Project-URL: Bug Reports, https://github.com/erkandem/calcbsimpvol/issues
Project-URL: Source, https://github.com/erkandem/calcbsimpvol
Keywords: options implied volatility option iv ivol options-on-futures ivsurface black-scholes
Platform: UNKNOWN
Classifier: Development Status :: 5 - Production/Stable
Classifier: Intended Audience :: Developers
Classifier: Intended Audience :: Education
Classifier: Intended Audience :: Financial and Insurance Industry
Classifier: Intended Audience :: Science/Research
Classifier: Topic :: Office/Business :: Financial 
Classifier: Topic :: Office/Business :: Financial :: Spreadsheet
Classifier: Operating System :: OS Independent
Classifier: License :: OSI Approved :: MIT License
Classifier: Programming Language :: Python :: 3
Classifier: Programming Language :: Python :: 3.4
Classifier: Programming Language :: Python :: 3.5
Classifier: Programming Language :: Python :: 3.6
Classifier: Programming Language :: Python :: 3.7
Requires-Dist: numpy
Requires-Dist: scipy
Requires-Dist: matplotlib
